{
    "fluentMethods": true,
    "relationships": [
        {
            "relationshipName": "country",
            "otherEntityName": "country",
            "relationshipType": "many-to-one",
            "otherEntityField": "countryName"
        }
    ],
    "fields": [
        {
            "fieldName": "streetAddress",
            "fieldType": "String"
        },
        {
            "fieldName": "postalCode",
            "fieldType": "String",
            "fieldValidateRules": [
                "required"
            ]
        },
        {
            "fieldName": "city",
            "fieldType": "String"
        },
        {
            "fieldName": "stateProvince",
            "fieldType": "String"
        }
    ],
    "changelogDate": "20170518121333",
    "dto": "no",
    "service": "no",
    "entityTableName": "location",
    "pagination": "no"
}
